{
    "$schema": "http://json-schema.org/draft-04/schema#",
    "$ref": "#/definitions/ImageCacheKeyProto",
    "definitions": {
        "ImageCacheKeyProto": {
            "properties": {
                "resourceKey": {
                    "type": "string"
                },
                "publicResourceKey": {
                    "type": "string"
                }
            },
            "additionalProperties": true,
            "type": "object",
            "title": "Image Cache Key Proto"
        }
    }
}